{
  "tests": "./system_tests/*_test.js",
  "timeout": 10000,
  "output": "./system_tests/output",
  "helpers": {
    "WebDriverIO": {
      "url": "http://localhost:3000",
      "browser": "chrome",
      "desiredCapabilities": {
        "chromeOptions": {
          "args": [
            "--headless",
            "--disable-gpu",
            "--window-size=800,600",
            "--no-sandbox"
          ]
        }
      }
    }
  },
  "include": {
    "I": "./system_tests/steps_file.js"
  },
  "bootstrap": false,
  "mocha": {},
  "name": "web"
}
